{"name":"wonka","versions":{"1.3.1":{"version":"1.3.1","dist":{"tarball":"https://registry.npmjs.org/wonka/-/wonka-1.3.1.tgz","shasum":"6388e39e64242e7feeeb41508cf545fc5f4ab8e4","integrity":"sha512-aW8FXIq76+rXuwloItYiBrzlvnTD7xs4iUJB8lhcpWawhKp6O6iOns/jizTG4cz6fbm/1lpPh/eiRDHJEJsBCQ=="},"bin":null,"dependencies":{"bs-rebel":"^0.2.3"},"optionalDependencies":{},"peerDependencies":{},"peerDependenciesMeta":{},"os":[],"cpu":[],"scripts":{"terser":"run-p terser:es terser:cjs","bundle":"microbundle --external none --no-compress --no-sourcemap --format es,cjs","clean":"bsb -clean-world","build":"bsb -make-world","prettier":"prettier --write ./dist/*.js","bundlesize":"bundlesize","test":"jest","prebundle":"rimraf ./dist","terser:cjs":"terser --config-file .terser.config.json -o ./dist/wonka.js ./dist/wonka.js","postbundle":"run-s terser prettier","test:watch":"jest --watch","prepublishOnly":"run-s clean build bundle test","coverage":"jest -c ./.jest.coverage.json --coverage","prebundlesize":"run-s bundle","watch":"bsb -make-world -w","terser:es":"terser --config-file .terser.config.json --module -o ./dist/wonka.es.js ./dist/wonka.es.js"}},"0.1.0-3":{"version":"0.1.0-3","dist":{"tarball":"https://registry.npmjs.org/wonka/-/wonka-0.1.0-3.tgz","shasum":"5050a905ab825173557295b3c9f01f8571e2dc7a","integrity":"sha512-WTDEc8XlaTQKOp3GPEyGHkqpa9kSVHbc2sSYSvSznnbTKCk+ofeX94Wz/GQzSwBBQuTCAJNAmPBHR9RhjcAGrQ=="},"bin":null,"dependencies":{},"optionalDependencies":{},"peerDependencies":{"bs-platform":">=2.2.0"},"peerDependenciesMeta":{},"os":[],"cpu":[],"scripts":{"test":"jest","coverage":"jest -c ./.jest.coverage.json --coverage","watch":"bsb -make-world -w","clean":"bsb -clean-world","prepublishOnly":"run-s clean build test bundle","build":"bsb -make-world","test:watch":"jest --watch","prebundle":"run-s build","bundle":"microbundle -i ./.index.js","bundlesize":"bundlesize","prebundlesize":"run-s bundle"}},"6.2.0":{"version":"6.2.0","dist":{"tarball":"https://registry.npmjs.org/wonka/-/wonka-6.2.0.tgz","shasum":"8abf30e88d7f98408321cce73063334a4baa302d","integrity":"sha512-xvHt2H7aLkai68f4DzuZamUvokDNDv1sYPc7BkqJv78MVpsh5dqS5S6P8PLhvkgLw5Rlz22BVtfuvWmT6vS05Q=="},"bin":null,"dependencies":{},"optionalDependencies":{},"peerDependencies":{},"peerDependenciesMeta":{},"os":[],"cpu":[],"scripts":{"test":"vitest run","postinstall":"node ./scripts/postinstall.js","check":"tsc","build":"rollup -c scripts/rollup.config.mjs","lint":"eslint --ext=js,ts .","clean":"rimraf dist node_modules/.cache"}},"3.1.0":{"version":"3.1.0","dist":{"tarball":"https://registry.npmjs.org/wonka/-/wonka-3.1.0.tgz","shasum":"5e9894d1aa653b55e9a738e942ff2e0f4cfc0324","integrity":"sha512-i+1twiLbuPBnsLmm0xy2UefeC2OPO5wXaGQHEN4/3Gp7QguoEieuSNZt2+gEU6UVJq/GecFkdAzGDFH60WpUAw=="},"bin":null,"dependencies":{},"optionalDependencies":{},"peerDependencies":{},"peerDependenciesMeta":{},"os":[],"cpu":[],"scripts":{"refmt":"bsrefmt --in-place **/**/*.{re,rei}","bundle":"rollup -c rollup.config.js","flowgen":"./scripts/generate-flow-files.js","clean":"bsb -clean-world","test:watch":"jest --watch","docs:build":"gatsby build","prepublishOnly":"run-s clean build bundle flowgen test","codecov":"codecov","test":"jest","coverage":"jest -c ./.jest.coverage.json --coverage","build":"bsb -make-world","watch":"bsb -make-world -w","docs:dev":"gatsby develop"}},"6.3.4":{"version":"6.3.4","dist":{"tarball":"https://registry.npmjs.org/wonka/-/wonka-6.3.4.tgz","shasum":"76eb9316e3d67d7febf4945202b5bdb2db534594","integrity":"sha512-CjpbqNtBGNAeyNS/9W6q3kSkKE52+FjIj7AkFlLr11s/VWGUu6a2CdYSdGxocIhIVjaW/zchesBQUKPVU69Cqg=="},"bin":null,"dependencies":{},"optionalDependencies":{},"peerDependencies":{},"peerDependenciesMeta":{},"os":[],"cpu":[],"scripts":{"clean":"rimraf dist node_modules/.cache","lint":"eslint --ext=js,ts .","build":"rollup -c scripts/rollup.config.mjs","check":"tsc","changeset:version":"changeset version && pnpm install --lockfile-only","changeset:publish":"changeset publish","test":"vitest run"}},"0.1.0-2":{"version":"0.1.0-2","dist":{"tarball":"https://registry.npmjs.org/wonka/-/wonka-0.1.0-2.tgz","shasum":"a92d003302075fcb66ae78f85241e4f5433e7528","integrity":"sha512-FS13VIU1oOhblWX1vm6u70riDjDzO6OHmD5UCXP+Z1hra2bM31kEEAx+UZV3Dc1GIFev/cnNnICH1Ip0QTmTcg=="},"bin":null,"dependencies":{},"optionalDependencies":{},"peerDependencies":{"bs-platform":">=2.2.0"},"peerDependenciesMeta":{},"os":[],"cpu":[],"scripts":{"test":"jest","test:watch":"jest --watch","build":"bsb -make-world","prepublishOnly":"run-s clean build test bundle","coverage":"jest -c ./.jest.coverage.json --coverage","bundlesize":"bundlesize","watch":"bsb -make-world -w","bundle":"microbundle -i ./.index.js","prebundle":"run-s build","prebundlesize":"run-s bundle","clean":"bsb -clean-world"}},"4.0.10":{"version":"4.0.10","dist":{"tarball":"https://registry.npmjs.org/wonka/-/wonka-4.0.10.tgz","shasum":"9739002b18fbc09dfc6cf1986743d35cdbd2fbe9","integrity":"sha512-mPBDKeU69lgH+OPd2x+mAb/ARwe2gMhRnQR05LDbZ4U7psq3l6m4QL38ET/JhYr0wtBWkHvW6PYTnqmwqqi76Q=="},"bin":null,"dependencies":{},"optionalDependencies":{},"peerDependencies":{},"peerDependenciesMeta":{},"os":[],"cpu":[],"scripts":{"flowgen":"./scripts/generate-flow-files.js","check":"run-s check:ts check:flow","clean":"run-s bs:clean bundle:clean","docs:build":"gatsby build","check:ts":"tsc --noEmit","bs:watch":"bsb -make-world -w","bundle":"rollup -c rollup.config.js","prepublishOnly":"run-s clean build check test","bundle:clean":"rimraf dist node_modules/.cache","test":"jest","check:flow":"flow focus-check ./src/helpers/Wonka_flow_test.js","bs:clean":"bsb -clean-world","build":"run-s bs:build bundle flowgen","refmt":"bsrefmt --in-place **/**/*.{re,rei}","bs:build":"bsb -make-world","docs:dev":"gatsby develop"}},"5.0.0-rc.1":{"version":"5.0.0-rc.1","dist":{"tarball":"https://registry.npmjs.org/wonka/-/wonka-5.0.0-rc.1.tgz","shasum":"4e8a109dda4fe14da10d748cf1955d4bc55a5e5a","integrity":"sha512-RD/ytJUeFq9+sYJaHKwafhehJ9VDWex581Ndy4+Gy6TIIi29G4Cr9zbkXYI24B5ytU7/6SkrCL4yHV3L2MyHeQ=="},"bin":null,"dependencies":{},"optionalDependencies":{},"peerDependencies":{},"peerDependenciesMeta":{},"os":[],"cpu":[],"scripts":{"test":"jest","bs:watch":"bsb -make-world -w","clean":"run-s bs:clean bundle:clean","docs:dev":"gatsby develop","flowgen":"./scripts/generate-flow-files.js","bundle:clean":"rimraf dist node_modules/.cache","bundle":"rollup -c rollup.config.js","bs:clean":"bsb -clean-world","build":"run-s bs:build bundle flowgen","check":"run-s check:ts check:flow","check:ts":"tsc --noEmit","docs:build":"gatsby build","refmt":"bsrefmt --in-place **/**/*.{re,rei}","bs:build":"bsb -make-world","check:flow":"flow focus-check ./src/helpers/Wonka_flow_test.js","prepublishOnly":"run-s clean build check test"}},"4.0.0-rc.2":{"version":"4.0.0-rc.2","dist":{"tarball":"https://registry.npmjs.org/wonka/-/wonka-4.0.0-rc.2.tgz","shasum":"e5b555e2a467c34784584736e5ef0735787d62b7","integrity":"sha512-X3NnmGLsaoAj/lv8ccXm4Nq+2VGsJP47ZOn3MbumTODC4d4+G9AF+2Huvmby1tz79CWjRzkK/GxpaTFKiEMEcw=="},"bin":null,"dependencies":{},"optionalDependencies":{},"peerDependencies":{},"peerDependenciesMeta":{},"os":[],"cpu":[],"scripts":{"docs:build":"gatsby build","clean":"run-s bs:clean bundle:clean","bs:build":"bsb -make-world","refmt":"bsrefmt --in-place **/**/*.{re,rei}","bundle":"rollup -c rollup.config.js","prepublishOnly":"run-s clean build bundle flowgen check test","bs:clean":"bsb -clean-world","check":"tsc --noEmit","bs:watch":"bsb -make-world -w","test":"jest","docs:dev":"gatsby develop","flowgen":"./scripts/generate-flow-files.js","build":"run-s bs:build bundle flowgen","bundle:clean":"rimraf dist node_modules/.cache"}},"6.3.2":{"version":"6.3.2","dist":{"tarball":"https://registry.npmjs.org/wonka/-/wonka-6.3.2.tgz","shasum":"6f32992b332251d7b696b038990f4dc284b3b33d","integrity":"sha512-2xXbQ1LnwNS7egVm1HPhW2FyKrekolzhpM3mCwXdQr55gO+tAiY76rhb32OL9kKsW8taj++iP7C6hxlVzbnvrw=="},"bin":null,"dependencies":{},"optionalDependencies":{},"peerDependencies":{},"peerDependenciesMeta":{},"os":[],"cpu":[],"scripts":{"changeset:version":"changeset version && pnpm install --lockfile-only","changeset:publish":"changeset publish","lint":"eslint --ext=js,ts .","check":"tsc","clean":"rimraf dist node_modules/.cache","build":"rollup -c scripts/rollup.config.mjs","test":"vitest run"}},"3.0.0-1.beta":{"version":"3.0.0-1.beta","dist":{"tarball":"https://registry.npmjs.org/wonka/-/wonka-3.0.0-1.beta.tgz","shasum":"8ffe35ca7083d41f3bfcfa6bf7b9855f5f255663","integrity":"sha512-m6BuyHD32l6ADgk+6TiB2k7sGXNoY3h79RoYJ+EC1kRLlCiavaEhS245Qzxf2RZNxuuXUaKfCOTBlNd8n+2opg=="},"bin":null,"dependencies":{},"optionalDependencies":{},"peerDependencies":{},"peerDependenciesMeta":{},"os":[],"cpu":[],"scripts":{"coverage":"jest -c ./.jest.coverage.json --coverage","bundle":"rollup -c rollup.config.js","watch":"bsb -make-world -w","test":"jest","flowgen":"./scripts/generate-flow-files.js","prepublishOnly":"run-s clean build bundle flowgen test","build":"bsb -make-world","refmt":"bsrefmt --in-place **/**/*.{re,rei}","clean":"bsb -clean-world","test:watch":"jest --watch"}},"0.0.0":{"version":"0.0.0","dist":{"tarball":"https://registry.npmjs.org/wonka/-/wonka-0.0.0.tgz","shasum":"5bb1016f9134aeb736c594af578a036519cebf24","integrity":"sha512-GKmKBvOVYgSFS9LGfEu7IBe3fTGHlQtuMW1Of7csHWP5yIL2EU9xguUYx3UIg39sBKuV+088NATcnEphJg1CLQ=="},"bin":null,"dependencies":{},"optionalDependencies":{},"peerDependencies":{},"peerDependenciesMeta":{},"os":[],"cpu":[],"scripts":{"test":"echo \"Error: no test specified\" && exit 1"}},"6.2.2":{"version":"6.2.2","dist":{"tarball":"https://registry.npmjs.org/wonka/-/wonka-6.2.2.tgz","shasum":"d43bf37a086d5854f833082cd83fd8a57387b977","integrity":"sha512-ajwayFBbenJPx27+3gUjqRJrZdLu6/10FWaLMDut8Wf9Y18qc5XGtCcWfsSV6W7ojmPVHVd9Qk924KGac0RL8g=="},"bin":null,"dependencies":{},"optionalDependencies":{},"peerDependencies":{},"peerDependenciesMeta":{},"os":[],"cpu":[],"scripts":{"clean":"rimraf dist node_modules/.cache","build":"rollup -c scripts/rollup.config.mjs","check":"tsc","test":"vitest run","lint":"eslint --ext=js,ts ."}},"1.3.0":{"version":"1.3.0","dist":{"tarball":"https://registry.npmjs.org/wonka/-/wonka-1.3.0.tgz","shasum":"7205c884f6d1d4ffac34958ea1caa46559734404","integrity":"sha512-lZ9R2DlPJWuxZ5gkRGG/VzoXMouonWeFF0Xba+Z5k9bT/OeyULwj8u4mdttoKMlTaYnHkgAZG1cJyjuxEltfag=="},"bin":null,"dependencies":{"bs-rebel":"^0.2.3"},"optionalDependencies":{},"peerDependencies":{},"peerDependenciesMeta":{},"os":[],"cpu":[],"scripts":{"bundle":"microbundle --external none --no-compress --no-sourcemap --format es,cjs","terser":"run-p terser:es terser:cjs","watch":"bsb -make-world -w","terser:cjs":"terser --config-file .terser.config.json -o ./dist/wonka.js ./dist/wonka.js","clean":"bsb -clean-world","terser:es":"terser --config-file .terser.config.json --module -o ./dist/wonka.es.js ./dist/wonka.es.js","bundlesize":"bundlesize","prepublishOnly":"run-s clean build bundle test","build":"bsb -make-world","prebundle":"rimraf ./dist","postbundle":"run-s terser prettier","test":"jest","test:watch":"jest --watch","prebundlesize":"run-s bundle","coverage":"jest -c ./.jest.coverage.json --coverage","prettier":"prettier --write ./dist/*.js"}},"2.0.2":{"version":"2.0.2","dist":{"tarball":"https://registry.npmjs.org/wonka/-/wonka-2.0.2.tgz","shasum":"6523631a0121b92f2ee5b95971a16335d1985e43","integrity":"sha512-xbWQpBlBOaNUeZj7IsgXMwE08HeomMQYkaUVoXIHgyAOk9bdfqOA9Ccw87cL1jgFbGOeXifO9OfgeL6vut9/8Q=="},"bin":null,"dependencies":{"bs-rebel":"^0.2.3"},"optionalDependencies":{},"peerDependencies":{},"peerDependenciesMeta":{},"os":[],"cpu":[],"scripts":{"prepublishOnly":"run-s clean build bundle test","bundle":"microbundle --external none --no-compress --no-sourcemap --format es,cjs","terser":"run-p terser:es terser:cjs","build":"bsb -make-world","postbundle":"run-s terser prettier","terser:es":"terser --config-file .terser.config.json --module -o ./dist/wonka.es.js ./dist/wonka.es.js","clean":"bsb -clean-world","watch":"bsb -make-world -w","prebundle":"rimraf ./dist","bundlesize":"bundlesize","refmt":"bsrefmt --in-place **/**/*.{re,rei}","test:watch":"jest --watch","prettier":"prettier --write ./dist/*.js","terser:cjs":"terser --config-file .terser.config.json -o ./dist/wonka.js ./dist/wonka.js","prebundlesize":"run-s bundle","test":"jest","coverage":"jest -c ./.jest.coverage.json --coverage"}},"4.0.15":{"version":"4.0.15","dist":{"tarball":"https://registry.npmjs.org/wonka/-/wonka-4.0.15.tgz","shasum":"9aa42046efa424565ab8f8f451fcca955bf80b89","integrity":"sha512-U0IUQHKXXn6PFo9nqsHphVCE5m3IntqZNB9Jjn7EB1lrR7YTDY3YWgFvEvwniTzXSvOH/XMzAZaIfJF/LvHYXg=="},"bin":null,"dependencies":{},"optionalDependencies":{},"peerDependencies":{},"peerDependenciesMeta":{},"os":[],"cpu":[],"scripts":{"check:flow":"flow focus-check ./src/helpers/Wonka_flow_test.js","flowgen":"./scripts/generate-flow-files.js","check":"run-s check:ts check:flow","bundle":"rollup -c rollup.config.js","bundle:clean":"rimraf dist node_modules/.cache","bs:watch":"bsb -make-world -w","docs:dev":"gatsby develop","refmt":"bsrefmt --in-place **/**/*.{re,rei}","test":"jest","clean":"run-s bs:clean bundle:clean","bs:clean":"bsb -clean-world","build":"run-s bs:build bundle flowgen","docs:build":"gatsby build","check:ts":"tsc --noEmit","prepublishOnly":"run-s clean build check test","bs:build":"bsb -make-world"}},"4.0.12":{"version":"4.0.12","dist":{"tarball":"https://registry.npmjs.org/wonka/-/wonka-4.0.12.tgz","shasum":"187ed0ae321ef90faa14ef71b3fff5d74b442e3b","integrity":"sha512-vaEFs/vkCu3SlHspSnYlPnXCJYa014PaI8zV3jpex4ivtHBIyG8miVAB5xQ6jlQDveV5hvgALIsdCJ7Ey7MpKg=="},"bin":null,"dependencies":{},"optionalDependencies":{},"peerDependencies":{},"peerDependenciesMeta":{},"os":[],"cpu":[],"scripts":{"docs:dev":"gatsby develop","build":"run-s bs:build bundle flowgen","bs:build":"bsb -make-world","bundle":"rollup -c rollup.config.js","bs:watch":"bsb -make-world -w","flowgen":"./scripts/generate-flow-files.js","refmt":"bsrefmt --in-place **/**/*.{re,rei}","docs:build":"gatsby build","prepublishOnly":"run-s clean build check test","clean":"run-s bs:clean bundle:clean","bs:clean":"bsb -clean-world","test":"jest","check:ts":"tsc --noEmit","bundle:clean":"rimraf dist node_modules/.cache","check:flow":"flow focus-check ./src/helpers/Wonka_flow_test.js","check":"run-s check:ts check:flow"}},"4.0.9":{"version":"4.0.9","dist":{"tarball":"https://registry.npmjs.org/wonka/-/wonka-4.0.9.tgz","shasum":"b21d93621e1d5f3b45ca96d99d03711c7c1f7c55","integrity":"sha512-he7Nn1254ToUN03zLbJok6QxKdRJd46/QHm8nUcJNViXQnCutCuUgAbZvzoxrX+VXzGb4sCFolC4XhkHsmvdaA=="},"bin":null,"dependencies":{},"optionalDependencies":{},"peerDependencies":{},"peerDependenciesMeta":{},"os":[],"cpu":[],"scripts":{"bs:clean":"bsb -clean-world","clean":"run-s bs:clean bundle:clean","bs:watch":"bsb -make-world -w","bundle:clean":"rimraf dist node_modules/.cache","bundle":"rollup -c rollup.config.js","check:ts":"tsc --noEmit","flowgen":"./scripts/generate-flow-files.js","docs:build":"gatsby build","test":"jest","refmt":"bsrefmt --in-place **/**/*.{re,rei}","prepublishOnly":"run-s clean build check test","check:flow":"flow focus-check ./src/helpers/Wonka_flow_test.js","check":"run-s check:ts check:flow","docs:dev":"gatsby develop","bs:build":"bsb -make-world","build":"run-s bs:build bundle flowgen"}},"0.0.0-canary-20230320012503":{"version":"0.0.0-canary-20230320012503","dist":{"tarball":"https://registry.npmjs.org/wonka/-/wonka-0.0.0-canary-20230320012503.tgz","shasum":"a4c69e05bec4e7f53d6fd75a90272a510f949227","integrity":"sha512-6hkZEoV/h0VTzEi7bMCGpRz7k3K/7H9+d5S1Mb/yHHZlMTVjHKHnbyCo41SzFNLwrYLdjA6drendLN9eFtwvjg=="},"bin":null,"dependencies":{},"optionalDependencies":{},"peerDependencies":{},"peerDependenciesMeta":{},"os":[],"cpu":[],"scripts":{"changeset:publish":"changeset publish","changeset:version":"changeset version && pnpm install --lockfile-only","check":"tsc","lint":"eslint --ext=js,ts .","test":"vitest run","clean":"rimraf dist node_modules/.cache","build":"rollup -c scripts/rollup.config.mjs"}},"0.1.0-1":{"version":"0.1.0-1","dist":{"tarball":"https://registry.npmjs.org/wonka/-/wonka-0.1.0-1.tgz","shasum":"e216a2b8f4ef3c0a2c7787583549a11f9be1ac09","integrity":"sha512-8xcIVk/dTHGKM8AK/rJfpLfjZkkRxQtpj/FWsl95tKDSKmXgk774AzILimXvefYopcMfPAlSuF76rWeD4rwd+g=="},"bin":null,"dependencies":{},"optionalDependencies":{},"peerDependencies":{"bs-platform":">=2.2.0"},"peerDependenciesMeta":{},"os":[],"cpu":[],"scripts":{"prebundle":"run-s build","bundle":"microbundle -i ./.index.js","clean":"bsb -clean-world","coverage":"jest -c ./.jest.coverage.json --coverage","test":"jest","prebundlesize":"run-s bundle","build":"bsb -make-world","test:watch":"jest --watch","prepublishOnly":"run-s clean build test bundle","watch":"bsb -make-world -w","bundlesize":"bundlesize"}},"1.4.4":{"version":"1.4.4","dist":{"tarball":"https://registry.npmjs.org/wonka/-/wonka-1.4.4.tgz","shasum":"ac216e4028dba706b529495f58b1efa507a230e7","integrity":"sha512-Ogjp2Hc+XhYx8ObUbetEtugAN3FmFKUiKdy3me3XsCfcCVOKIuqEXZDplz/x8/jh2dPyKcVQ8zSi9Li2eeitvw=="},"bin":null,"dependencies":{"bs-rebel":"^0.2.3"},"optionalDependencies":{},"peerDependencies":{},"peerDependenciesMeta":{},"os":[],"cpu":[],"scripts":{"coverage":"jest -c ./.jest.coverage.json --coverage","prettier":"prettier --write ./dist/*.js","build":"bsb -make-world","bundle":"microbundle --external none --no-compress --no-sourcemap --format es,cjs","terser":"run-p terser:es terser:cjs","terser:cjs":"terser --config-file .terser.config.json -o ./dist/wonka.js ./dist/wonka.js","watch":"bsb -make-world -w","clean":"bsb -clean-world","bundlesize":"bundlesize","terser:es":"terser --config-file .terser.config.json --module -o ./dist/wonka.es.js ./dist/wonka.es.js","prebundlesize":"run-s bundle","prepublishOnly":"run-s clean build bundle test","test:watch":"jest --watch","test":"jest","postbundle":"run-s terser prettier","prebundle":"rimraf ./dist"}},"0.1.0-5":{"version":"0.1.0-5","dist":{"tarball":"https://registry.npmjs.org/wonka/-/wonka-0.1.0-5.tgz","shasum":"ad118e6098c5cc139822da42c880ef5b65ba7290","integrity":"sha512-Z84oTJS1h6++fyEdQwNmdZPzDb+GP9QwzG7wAEtuu+rPnzg0WAO+g/AfbPerOiNeu1OEmiDrSUgw4g2MfdwJPw=="},"bin":null,"dependencies":{},"optionalDependencies":{},"peerDependencies":{"bs-platform":">=2.2.0"},"peerDependenciesMeta":{},"os":[],"cpu":[],"scripts":{"build":"bsb -make-world","prebundlesize":"run-s bundle","test:watch":"jest --watch","bundle":"microbundle -i ./.index.js","test":"jest","bundlesize":"bundlesize","clean":"bsb -clean-world","prepublishOnly":"run-s clean build test bundle","watch":"bsb -make-world -w","prebundle":"run-s build","coverage":"jest -c ./.jest.coverage.json --coverage"}},"2.0.0":{"version":"2.0.0","dist":{"tarball":"https://registry.npmjs.org/wonka/-/wonka-2.0.0.tgz","shasum":"c71311db41c12806f991f0e50f3c95ae7305c87f","integrity":"sha512-25ZnFMci8KMuvkO3+h1UhGq2QXPY0Jbwq+GwF3bQbaMElVVuLHDum17HUCugHl+gAokwMflsHfTMfO5kSukbvw=="},"bin":null,"dependencies":{"bs-rebel":"^0.2.3"},"optionalDependencies":{},"peerDependencies":{},"peerDependenciesMeta":{},"os":[],"cpu":[],"scripts":{"bundle":"microbundle --external none --no-compress --no-sourcemap --format es,cjs","terser:es":"terser --config-file .terser.config.json --module -o ./dist/wonka.es.js ./dist/wonka.es.js","test":"jest","terser":"run-p terser:es terser:cjs","prebundle":"rimraf ./dist","postbundle":"run-s terser prettier","test:watch":"jest --watch","terser:cjs":"terser --config-file .terser.config.json -o ./dist/wonka.js ./dist/wonka.js","prepublishOnly":"run-s clean build bundle test","prebundlesize":"run-s bundle","coverage":"jest -c ./.jest.coverage.json --coverage","clean":"bsb -clean-world","bundlesize":"bundlesize","prettier":"prettier --write ./dist/*.js","build":"bsb -make-world","watch":"bsb -make-world -w"}},"4.0.11":{"version":"4.0.11","dist":{"tarball":"https://registry.npmjs.org/wonka/-/wonka-4.0.11.tgz","shasum":"3edfea465f355b8e9e5776dd25403042747d63a4","integrity":"sha512-WpAu3tB6HtTLxChp9DdM3dxW8/ptaPombCdamVt+dFhwXIUWrvlI8boF916z4nAI8toc4pC+ZkWo3iQcj/i7vg=="},"bin":null,"dependencies":{},"optionalDependencies":{},"peerDependencies":{},"peerDependenciesMeta":{},"os":[],"cpu":[],"scripts":{"bs:build":"bsb -make-world","test":"jest","bundle:clean":"rimraf dist node_modules/.cache","check:flow":"flow focus-check ./src/helpers/Wonka_flow_test.js","bs:clean":"bsb -clean-world","build":"run-s bs:build bundle flowgen","refmt":"bsrefmt --in-place **/**/*.{re,rei}","check:ts":"tsc --noEmit","clean":"run-s bs:clean bundle:clean","prepublishOnly":"run-s clean build check test","bundle":"rollup -c rollup.config.js","flowgen":"./scripts/generate-flow-files.js","docs:dev":"gatsby develop","bs:watch":"bsb -make-world -w","check":"run-s check:ts check:flow","docs:build":"gatsby build"}},"6.2.5":{"version":"6.2.5","dist":{"tarball":"https://registry.npmjs.org/wonka/-/wonka-6.2.5.tgz","shasum":"26e54a6827b96a6164b845106f4d925ede4089bb","integrity":"sha512-adhGYKm5xWIZYXRkzEqHbRbRl2gXHqOudjQJMXpRgSyboFmaKOjGm3RIThBk4tZdiZx1DXuKK0H9wKBgXHhzZg=="},"bin":null,"dependencies":{},"optionalDependencies":{},"peerDependencies":{},"peerDependenciesMeta":{},"os":[],"cpu":[],"scripts":{"check":"tsc","lint":"eslint --ext=js,ts .","changeset:version":"changeset version && pnpm install --lockfile-only","changeset:publish":"changeset publish","build":"rollup -c scripts/rollup.config.mjs","clean":"rimraf dist node_modules/.cache","test":"vitest run"}},"1.1.0":{"version":"1.1.0","dist":{"tarball":"https://registry.npmjs.org/wonka/-/wonka-1.1.0.tgz","shasum":"f8c7d0ff9ce1564df40f9f647f3f919cdd5d5b66","integrity":"sha512-f3lg0weCNZme+fcAn7jDsCt34BvGynxoZmBZFyfcOGdYNKcIk7OcN+OEUjQtfY0PvPFW6oeUr3mnwPVyPvb1Mw=="},"bin":null,"dependencies":{},"optionalDependencies":{},"peerDependencies":{},"peerDependenciesMeta":{},"os":[],"cpu":[],"scripts":{"test":"jest","build":"bsb -make-world","prebundlesize":"run-s bundle","watch":"bsb -make-world -w","coverage":"jest -c ./.jest.coverage.json --coverage","bundle":"microbundle --no-compress --format es,cjs","test:watch":"jest --watch","prepublishOnly":"run-s clean build bundle test","clean":"bsb -clean-world","bundlesize":"bundlesize"}},"0.0.0-canary-20230327141302":{"version":"0.0.0-canary-20230327141302","dist":{"tarball":"https://registry.npmjs.org/wonka/-/wonka-0.0.0-canary-20230327141302.tgz","shasum":"b3fc2b5cf771fa0797184c8a2e078c4256c72d7d","integrity":"sha512-7ZPt/RVG45pgxbrd0PU8SlSpEjcX4XRjPJnEHgipokkSklax0KUl/tzN/9FX0iavH9ojDytAhjr2NCC1rKbCLA=="},"bin":null,"dependencies":{},"optionalDependencies":{},"peerDependencies":{},"peerDependenciesMeta":{},"os":[],"cpu":[],"scripts":{"check":"tsc","lint":"eslint --ext=js,ts .","clean":"rimraf dist node_modules/.cache","changeset:version":"changeset version && pnpm install --lockfile-only","changeset:publish":"changeset publish","build":"rollup -c scripts/rollup.config.mjs","test":"vitest run"}},"1.0.0":{"version":"1.0.0","dist":{"tarball":"https://registry.npmjs.org/wonka/-/wonka-1.0.0.tgz","shasum":"bba524e9e5d684858d603a217ab0545fbfdf56b0","integrity":"sha512-UfI4PwersOKrN8EWR2t1oADp32WUeCWVwz7LMH+IqnP1hbhAjZmDtgnNODMJiYOYfDlAV9WAjXFLcbO73b8OMQ=="},"bin":null,"dependencies":{},"optionalDependencies":{},"peerDependencies":{"bs-platform":">=2.2.0"},"peerDependenciesMeta":{},"os":[],"cpu":[],"scripts":{"build":"bsb -make-world","bundle":"microbundle -i ./.index.js","clean":"bsb -clean-world","coverage":"jest -c ./.jest.coverage.json --coverage","test:watch":"jest --watch","prebundle":"run-s build","prebundlesize":"run-s bundle","bundlesize":"bundlesize","watch":"bsb -make-world -w","test":"jest","prepublishOnly":"run-s clean build test bundle"}},"0.0.0-canary-20230326035503":{"version":"0.0.0-canary-20230326035503","dist":{"tarball":"https://registry.npmjs.org/wonka/-/wonka-0.0.0-canary-20230326035503.tgz","shasum":"45195ebb7ef7c0b5aa3d7d06fbf1cadc59d673be","integrity":"sha512-3AoUAPNq8wlG/Q3Ke71rPA2Kt6myHFQ+5+ut4z4e0AEdMi/atmwoqTzslR4U7YOnU/GtwLNERI28RGeKpxOMOw=="},"bin":null,"dependencies":{},"optionalDependencies":{},"peerDependencies":{},"peerDependenciesMeta":{},"os":[],"cpu":[],"scripts":{"test":"vitest run","clean":"rimraf dist node_modules/.cache","build":"rollup -c scripts/rollup.config.mjs","check":"tsc","changeset:publish":"changeset publish","lint":"eslint --ext=js,ts .","changeset:version":"changeset version && pnpm install --lockfile-only"}},"1.1.5":{"version":"1.1.5","dist":{"tarball":"https://registry.npmjs.org/wonka/-/wonka-1.1.5.tgz","shasum":"3ddec075249c4173df016abd31aeb6c5359cc954","integrity":"sha512-H2cgUy2aVtenLubcWN4IzU5FqXN1jPbT+J/HjavlDyUk5XZ9oOjTQQ4sRanZNc+Sswsbk4PQ7NF96k4LQ02lsQ=="},"bin":null,"dependencies":{"bs-rebel":"^0.2.3"},"optionalDependencies":{},"peerDependencies":{},"peerDependenciesMeta":{},"os":[],"cpu":[],"scripts":{"terser":"run-p terser:es terser:cjs","test:watch":"jest --watch","prettier":"prettier --write ./dist/*.js","bundlesize":"bundlesize","prebundlesize":"run-s bundle","terser:es":"terser --config-file .terser.config.json --module -o ./dist/wonka.es.js ./dist/wonka.es.js","prepublishOnly":"run-s clean build bundle test","postbundle":"run-s terser prettier","coverage":"jest -c ./.jest.coverage.json --coverage","watch":"bsb -make-world -w","test":"jest","build":"bsb -make-world","terser:cjs":"terser --config-file .terser.config.json -o ./dist/wonka.js ./dist/wonka.js","prebundle":"rimraf ./dist","clean":"bsb -clean-world","bundle":"microbundle --external none --no-compress --no-sourcemap --format es,cjs"}},"1.1.2":{"version":"1.1.2","dist":{"tarball":"https://registry.npmjs.org/wonka/-/wonka-1.1.2.tgz","shasum":"62699075b3d6fa98d3a27e17a7af9a4e38525fd3","integrity":"sha512-1sIDG8CZrltcB0882jaay73jsFjDu1rPIXo6BNS9XFFv2DDs47qZ1JDGikq4AywuN60ODOEm0/s5QzdSXFfvhA=="},"bin":null,"dependencies":{"bs-rebel":"^0.2.3"},"optionalDependencies":{},"peerDependencies":{},"peerDependenciesMeta":{},"os":[],"cpu":[],"scripts":{"prebundlesize":"run-s bundle","test":"jest","test:watch":"jest --watch","clean":"run-p clean:bs clean:dist","build":"bsb -make-world","bundle":"microbundle --no-compress --format es,cjs","clean:dist":"rimraf dist","bundlesize":"bundlesize","coverage":"jest -c ./.jest.coverage.json --coverage","watch":"bsb -make-world -w","prepublishOnly":"run-s clean build bundle test","clean:bs":"bsb -clean-world"}},"5.0.0-rc.0":{"version":"5.0.0-rc.0","dist":{"tarball":"https://registry.npmjs.org/wonka/-/wonka-5.0.0-rc.0.tgz","shasum":"843d5cdd33cdbb1c9751966c1bb9d5db113ab5f1","integrity":"sha512-UUW3SIPsoir30lIEDguCda5l+D/ge3hhkHL2f8TiUcorzMT46rN5wMAmOZ6T6X3VHm2AZdpF7NCZCCQAfALcCw=="},"bin":null,"dependencies":{},"optionalDependencies":{},"peerDependencies":{},"peerDependenciesMeta":{},"os":[],"cpu":[],"scripts":{"prepublishOnly":"run-s clean build check test","check:ts":"tsc --noEmit","bs:clean":"bsb -clean-world","refmt":"bsrefmt --in-place **/**/*.{re,rei}","test":"jest","clean":"run-s bs:clean bundle:clean","check":"run-s check:ts check:flow","bs:watch":"bsb -make-world -w","docs:dev":"gatsby develop","bs:build":"bsb -make-world","bundle":"rollup -c rollup.config.js","check:flow":"flow focus-check ./src/helpers/Wonka_flow_test.js","bundle:clean":"rimraf dist node_modules/.cache","docs:build":"gatsby build","flowgen":"./scripts/generate-flow-files.js","build":"run-s bs:build bundle flowgen"}},"4.0.8":{"version":"4.0.8","dist":{"tarball":"https://registry.npmjs.org/wonka/-/wonka-4.0.8.tgz","shasum":"edab5fb3bcb060242b7a47d2aaab57a45ef69c35","integrity":"sha512-7JHs16U9/OxkkoytluIRfxRLML7erwWuDkE5Qgw+12ctIBjUwq+wIifzTvJXi9NDSO+Hr9I6t/huiLaeWg89vA=="},"bin":null,"dependencies":{},"optionalDependencies":{},"peerDependencies":{},"peerDependenciesMeta":{},"os":[],"cpu":[],"scripts":{"refmt":"bsrefmt --in-place **/**/*.{re,rei}","bundle":"rollup -c rollup.config.js","check:flow":"flow focus-check ./src/helpers/Wonka_flow_test.js","bundle:clean":"rimraf dist node_modules/.cache","docs:build":"gatsby build","clean":"run-s bs:clean bundle:clean","test":"jest","check":"run-s check:ts check:flow","bs:watch":"bsb -make-world -w","docs:dev":"gatsby develop","bs:clean":"bsb -clean-world","build":"run-s bs:build bundle flowgen","check:ts":"tsc --noEmit","flowgen":"./scripts/generate-flow-files.js","prepublishOnly":"run-s clean build check test","bs:build":"bsb -make-world"}},"1.4.2":{"version":"1.4.2","dist":{"tarball":"https://registry.npmjs.org/wonka/-/wonka-1.4.2.tgz","shasum":"fc9e05e34c196ba140519e8f790929d1a49ef905","integrity":"sha512-a/30MF1TEbF9FGuCRUQZuTUPz7qHNeWPuybtwKLx8qCbMqHeThMCXJbEjQho0htqJquLjTp0Nn3Obm0V+dCDmQ=="},"bin":null,"dependencies":{"bs-rebel":"^0.2.3"},"optionalDependencies":{},"peerDependencies":{},"peerDependenciesMeta":{},"os":[],"cpu":[],"scripts":{"prepublishOnly":"run-s clean build bundle test","test:watch":"jest --watch","test":"jest","terser:cjs":"terser --config-file .terser.config.json -o ./dist/wonka.js ./dist/wonka.js","bundlesize":"bundlesize","clean":"bsb -clean-world","terser:es":"terser --config-file .terser.config.json --module -o ./dist/wonka.es.js ./dist/wonka.es.js","prebundlesize":"run-s bundle","terser":"run-p terser:es terser:cjs","build":"bsb -make-world","bundle":"microbundle --external none --no-compress --no-sourcemap --format es,cjs","prebundle":"rimraf ./dist","postbundle":"run-s terser prettier","coverage":"jest -c ./.jest.coverage.json --coverage","watch":"bsb -make-world -w","prettier":"prettier --write ./dist/*.js"}},"4.0.0-rc.4":{"version":"4.0.0-rc.4","dist":{"tarball":"https://registry.npmjs.org/wonka/-/wonka-4.0.0-rc.4.tgz","shasum":"d1f3f02da44c6b50fb3d463c72c92a8fa8368ae4","integrity":"sha512-gIFR1GrKYvPHMeq8l2Umxqkr0HOmgAV5ikXnilNfoq7FgUXY8j88gSF6gFi5rtfUGX4T/E3SLvtqm5ovyT1k3A=="},"bin":null,"dependencies":{},"optionalDependencies":{},"peerDependencies":{},"peerDependenciesMeta":{},"os":[],"cpu":[],"scripts":{"bs:clean":"bsb -clean-world","docs:build":"gatsby build","flowgen":"./scripts/generate-flow-files.js","bs:build":"bsb -make-world","clean":"run-s bs:clean bundle:clean","prepublishOnly":"run-s clean build check test","check":"tsc --noEmit","build":"run-s bs:build bundle flowgen","bundle":"rollup -c rollup.config.js","bs:watch":"bsb -make-world -w","test":"jest","refmt":"bsrefmt --in-place **/**/*.{re,rei}","bundle:clean":"rimraf dist node_modules/.cache","docs:dev":"gatsby develop"}},"6.1.0":{"version":"6.1.0","dist":{"tarball":"https://registry.npmjs.org/wonka/-/wonka-6.1.0.tgz","shasum":"65297ebf7031ae46d4b0c56da93950fb3ae5baaa","integrity":"sha512-VgiMCz7BXOiDbgpVhf5iNhK7hurteY5Jv0fDJewUkY0s4fbxQD2iKqfGxNXNTwp2v3bgT8QVu2l5H7YdkZ5WIA=="},"bin":null,"dependencies":{},"optionalDependencies":{},"peerDependencies":{},"peerDependenciesMeta":{},"os":[],"cpu":[],"scripts":{"lint":"eslint --ext=js,ts .","clean":"rimraf dist node_modules/.cache","test":"jest","prepublishOnly":"run-s clean build check test","check":"tsc","build":"rollup -c rollup.config.js"}},"6.2.3":{"version":"6.2.3","dist":{"tarball":"https://registry.npmjs.org/wonka/-/wonka-6.2.3.tgz","shasum":"88f7852a23a3d53bca7411c70d66e9ce8f93a366","integrity":"sha512-EFOYiqDeYLXSzGYt2X3aVe9Hq1XJG+Hz/HjTRRT4dZE9q95khHl5+7pzUSXI19dbMO1/2UMrTf7JT7/7JrSQSQ=="},"bin":null,"dependencies":{},"optionalDependencies":{},"peerDependencies":{},"peerDependenciesMeta":{},"os":[],"cpu":[],"scripts":{"clean":"rimraf dist node_modules/.cache","test":"vitest run","lint":"eslint --ext=js,ts .","check":"tsc","build":"rollup -c scripts/rollup.config.mjs"}},"4.0.3":{"version":"4.0.3","dist":{"tarball":"https://registry.npmjs.org/wonka/-/wonka-4.0.3.tgz","shasum":"95babdc479714232c11dcd99093ab2fee47842d8","integrity":"sha512-lwSDBv375yZYC+P4sQxhZfF9izvtsdBZxRt4r5eHLmJdCFjQu500zqSO73rxXpRuoPgJtS3/BCiwOxHcBeftjg=="},"bin":null,"dependencies":{},"optionalDependencies":{},"peerDependencies":{},"peerDependenciesMeta":{},"os":[],"cpu":[],"scripts":{"test":"jest","docs:dev":"gatsby develop","bs:clean":"bsb -clean-world","docs:build":"gatsby build","refmt":"bsrefmt --in-place **/**/*.{re,rei}","check":"tsc --noEmit","bundle:clean":"rimraf dist node_modules/.cache","clean":"run-s bs:clean bundle:clean","bs:build":"bsb -make-world","bs:watch":"bsb -make-world -w","flowgen":"./scripts/generate-flow-files.js","bundle":"rollup -c rollup.config.js","build":"run-s bs:build bundle flowgen","prepublishOnly":"run-s clean build check test"}},"6.3.0":{"version":"6.3.0","dist":{"tarball":"https://registry.npmjs.org/wonka/-/wonka-6.3.0.tgz","shasum":"dd508dc9ef8588e5bbb10b96f2388bd9d4a1f17b","integrity":"sha512-7np+Kj4OnDQeEN0kafYLkPFKj1Qo+k7mNgyMHSgOeg+9AEvJbL8ipTBgSCTQfGcgVo6TPNU4T5+AZ2rAOyVrAw=="},"bin":null,"dependencies":{},"optionalDependencies":{},"peerDependencies":{},"peerDependenciesMeta":{},"os":[],"cpu":[],"scripts":{"test":"vitest run","check":"tsc","build":"rollup -c scripts/rollup.config.mjs","clean":"rimraf dist node_modules/.cache","changeset:version":"changeset version && pnpm install --lockfile-only","changeset:publish":"changeset publish","lint":"eslint --ext=js,ts ."}},"1.4.1":{"version":"1.4.1","dist":{"tarball":"https://registry.npmjs.org/wonka/-/wonka-1.4.1.tgz","shasum":"59c6756d9fe8858cd85a680d43ce3680572aca01","integrity":"sha512-5xpLGVbbeyRYxBX5EFwLHkb9I2H94bWZ9Zfa4CTwrIQwj2NX11Hc+3lVa+CA48T87Tp17/lRCZapVqWOgnDFlQ=="},"bin":null,"dependencies":{"bs-rebel":"^0.2.3"},"optionalDependencies":{},"peerDependencies":{},"peerDependenciesMeta":{},"os":[],"cpu":[],"scripts":{"terser:es":"terser --config-file .terser.config.json --module -o ./dist/wonka.es.js ./dist/wonka.es.js","build":"bsb -make-world","terser":"run-p terser:es terser:cjs","watch":"bsb -make-world -w","test":"jest","bundle":"microbundle --external none --no-compress --no-sourcemap --format es,cjs","bundlesize":"bundlesize","prettier":"prettier --write ./dist/*.js","test:watch":"jest --watch","prebundlesize":"run-s bundle","postbundle":"run-s terser prettier","prepublishOnly":"run-s clean build bundle test","clean":"bsb -clean-world","coverage":"jest -c ./.jest.coverage.json --coverage","terser:cjs":"terser --config-file .terser.config.json -o ./dist/wonka.js ./dist/wonka.js","prebundle":"rimraf ./dist"}},"1.4.3":{"version":"1.4.3","dist":{"tarball":"https://registry.npmjs.org/wonka/-/wonka-1.4.3.tgz","shasum":"4d7cdf341e7abcb2c80fecedee2f0839552c11f3","integrity":"sha512-IPdJ4HlWAhZbieKPKNE+W7HPcBv/kbvNN7pkUEZMO3oo80ayuCLnU48dM8c8XohGqWE3sggaVR0jvsCLMQ1Eug=="},"bin":null,"dependencies":{"bs-rebel":"^0.2.3"},"optionalDependencies":{},"peerDependencies":{},"peerDependenciesMeta":{},"os":[],"cpu":[],"scripts":{"prebundlesize":"run-s bundle","prepublishOnly":"run-s clean build bundle test","prettier":"prettier --write ./dist/*.js","bundle":"microbundle --external none --no-compress --no-sourcemap --format es,cjs","test:watch":"jest --watch","terser:es":"terser --config-file .terser.config.json --module -o ./dist/wonka.es.js ./dist/wonka.es.js","watch":"bsb -make-world -w","terser":"run-p terser:es terser:cjs","build":"bsb -make-world","test":"jest","postbundle":"run-s terser prettier","coverage":"jest -c ./.jest.coverage.json --coverage","clean":"bsb -clean-world","bundlesize":"bundlesize","prebundle":"rimraf ./dist","terser:cjs":"terser --config-file .terser.config.json -o ./dist/wonka.js ./dist/wonka.js"}},"1.1.1":{"version":"1.1.1","dist":{"tarball":"https://registry.npmjs.org/wonka/-/wonka-1.1.1.tgz","shasum":"28fff242f97058030b0386f9384aac19ab0f3903","integrity":"sha512-gzd2uUeeZp5ISaGSVkRb0BrXRFUO8HvlWZAsGO2nFYGWJ3ZnMKvsx6L82RoMAZUhJDJ1qPbKyieWzGtoPGuMDA=="},"bin":null,"dependencies":{"bs-rebel":"^0.2.3"},"optionalDependencies":{},"peerDependencies":{},"peerDependenciesMeta":{},"os":[],"cpu":[],"scripts":{"prepublishOnly":"run-s clean build bundle test","prebundlesize":"run-s bundle","bundlesize":"bundlesize","clean":"bsb -clean-world","test":"jest","coverage":"jest -c ./.jest.coverage.json --coverage","build":"bsb -make-world","bundle":"microbundle --no-compress --format es,cjs","watch":"bsb -make-world -w","test:watch":"jest --watch"}},"3.0.0":{"version":"3.0.0","dist":{"tarball":"https://registry.npmjs.org/wonka/-/wonka-3.0.0.tgz","shasum":"4f32a6a30e3229bae5944f002ce32d05b0423ba8","integrity":"sha512-eDDzMU1gv1OgZG0fYom/0xi3WO4s2ILt6QvZzjcnSvFM+nzpgX4sux1+Z+LDYWhknJA9agpDADVtATZtajMtLA=="},"bin":null,"dependencies":{},"optionalDependencies":{},"peerDependencies":{},"peerDependenciesMeta":{},"os":[],"cpu":[],"scripts":{"bundle":"rollup -c rollup.config.js","watch":"bsb -make-world -w","test":"jest","coverage":"jest -c ./.jest.coverage.json --coverage","flowgen":"./scripts/generate-flow-files.js","build":"bsb -make-world","clean":"bsb -clean-world","refmt":"bsrefmt --in-place **/**/*.{re,rei}","prepublishOnly":"run-s clean build bundle flowgen test","test:watch":"jest --watch"}},"0.0.0-canary-20230321073435":{"version":"0.0.0-canary-20230321073435","dist":{"tarball":"https://registry.npmjs.org/wonka/-/wonka-0.0.0-canary-20230321073435.tgz","shasum":"eaa1eff19f984b9a82252839707be4a0f101e3b7","integrity":"sha512-Q+ZfSlFR477Budt2FGB4++rpfgkbDgBjNPuup2kSPeqXj+HBl33txZ3KLprqOa99l6jQmkOtkZ7aLtBcnpmd0A=="},"bin":null,"dependencies":{},"optionalDependencies":{},"peerDependencies":{},"peerDependenciesMeta":{},"os":[],"cpu":[],"scripts":{"changeset:version":"changeset version && pnpm install --lockfile-only","lint":"eslint --ext=js,ts .","clean":"rimraf dist node_modules/.cache","changeset:publish":"changeset publish","check":"tsc","build":"rollup -c scripts/rollup.config.mjs","test":"vitest run"}},"6.3.3":{"version":"6.3.3","dist":{"tarball":"https://registry.npmjs.org/wonka/-/wonka-6.3.3.tgz","shasum":"aa99fa5f9303a32517497918fdd0208175e7edbe","integrity":"sha512-id4wYGsT6aEc8/3+by7NTHvTe0DwsOjv7vah0K0+AorV1MHKuS3OQ2g8DGsem1OEXrNShbVLPsg4kG2O6GZ2SQ=="},"bin":null,"dependencies":{},"optionalDependencies":{},"peerDependencies":{},"peerDependenciesMeta":{},"os":[],"cpu":[],"scripts":{"build":"rollup -c scripts/rollup.config.mjs","changeset:version":"changeset version && pnpm install --lockfile-only","changeset:publish":"changeset publish","check":"tsc","test":"vitest run","clean":"rimraf dist node_modules/.cache","lint":"eslint --ext=js,ts ."}},"0.0.0-canary-20230311000822":{"version":"0.0.0-canary-20230311000822","dist":{"tarball":"https://registry.npmjs.org/wonka/-/wonka-0.0.0-canary-20230311000822.tgz","shasum":"01814479f1533809b03d88b871b08b77b56fcd04","integrity":"sha512-dGF6KVOZhXsfhi/PCMWtYq5dVbU9U2uwrznXTTqqCYsnmyPZ9fOilaXOnfWKc65LiI1ubMfSbOvRZZPN8Idc0w=="},"bin":null,"dependencies":{},"optionalDependencies":{},"peerDependencies":{},"peerDependenciesMeta":{},"os":[],"cpu":[],"scripts":{"changeset:version":"changeset version && pnpm install --lockfile-only","changeset:publish":"changeset publish","test":"vitest run","check":"tsc","lint":"eslint --ext=js,ts .","build":"rollup -c scripts/rollup.config.mjs","clean":"rimraf dist node_modules/.cache"}},"3.2.0":{"version":"3.2.0","dist":{"tarball":"https://registry.npmjs.org/wonka/-/wonka-3.2.0.tgz","shasum":"40b9ce8e0c375127437661290e98e5d9e5278440","integrity":"sha512-sHCLouGzTclUlp1sdXAhuTqGMIoAQfpBit9puepaINPVqDBRtC8DPWtTUHC0DJIdFSO+DsO86AFBFCDor7Sn0g=="},"bin":null,"dependencies":{},"optionalDependencies":{},"peerDependencies":{},"peerDependenciesMeta":{},"os":[],"cpu":[],"scripts":{"codecov":"codecov","check":"tsc --noEmit","watch":"bsb -make-world -w","refmt":"bsrefmt --in-place **/**/*.{re,rei}","prepublishOnly":"run-s clean build bundle flowgen check test","docs:build":"gatsby build","build":"bsb -make-world","test":"jest","flowgen":"./scripts/generate-flow-files.js","clean":"bsb -clean-world","docs:dev":"gatsby develop","test:watch":"jest --watch","bundle":"rollup -c rollup.config.js","coverage":"jest -c ./.jest.coverage.json --coverage"}},"3.2.2":{"version":"3.2.2","dist":{"tarball":"https://registry.npmjs.org/wonka/-/wonka-3.2.2.tgz","shasum":"4d5c79fee2e6042066ba7aa86bd2f180487cc0c3","integrity":"sha512-btmYyFDuDpJXJfELkFkoTjfyn0M+/a54/kjqt3qGN/h/90A8Ynq8qxG4b0uXBAOvJNRnWnL8+d0C3r6Clt8PYA=="},"bin":null,"dependencies":{},"optionalDependencies":{},"peerDependencies":{},"peerDependenciesMeta":{},"os":[],"cpu":[],"scripts":{"check":"tsc --noEmit","clean":"bsb -clean-world","test:watch":"jest --watch","watch":"bsb -make-world -w","test":"jest","refmt":"bsrefmt --in-place **/**/*.{re,rei}","flowgen":"./scripts/generate-flow-files.js","coverage":"jest -c ./.jest.coverage.json --coverage","prepublishOnly":"run-s clean build bundle flowgen check test","codecov":"codecov","bundle":"rollup -c rollup.config.js","docs:build":"gatsby build","build":"bsb -make-world","docs:dev":"gatsby develop"}},"6.3.3-canary-c160e1d":{"version":"6.3.3-canary-c160e1d","dist":{"tarball":"https://registry.npmjs.org/wonka/-/wonka-6.3.3-canary-c160e1d.tgz","shasum":"6af5cade701222602b5709077b2814b4ab207651","integrity":"sha512-HJsl9nm48N39PU4DnMtrMIPnDAk1zpcPvYf1tzpv3Kg1dcbfBgo/Xa3WXkk0YboxO+HCK5nvn+mXgo4+i7guxQ=="},"bin":null,"dependencies":{},"optionalDependencies":{},"peerDependencies":{},"peerDependenciesMeta":{},"os":[],"cpu":[],"scripts":{"changeset:publish":"changeset publish","test":"vitest run","build":"rollup -c scripts/rollup.config.mjs","check":"tsc","changeset:version":"changeset version && pnpm install --lockfile-only","clean":"rimraf dist node_modules/.cache","lint":"eslint --ext=js,ts ."}},"4.0.5":{"version":"4.0.5","dist":{"tarball":"https://registry.npmjs.org/wonka/-/wonka-4.0.5.tgz","shasum":"3384b90ed8c1e6e182d6e2fb18468c33ab94e0af","integrity":"sha512-XKnzSpsk2UcPfyjecdc14b7LZSPeOEhYEs+/oAZ+gXV9BuYIcZC3hpapFi2DFHj1Bk38/npusgkiSD0+KdyCzQ=="},"bin":null,"dependencies":{},"optionalDependencies":{},"peerDependencies":{},"peerDependenciesMeta":{},"os":[],"cpu":[],"scripts":{"prepublishOnly":"run-s clean build check test","test":"jest","docs:build":"gatsby build","bs:build":"bsb -make-world","check":"tsc --noEmit","refmt":"bsrefmt --in-place **/**/*.{re,rei}","flowgen":"./scripts/generate-flow-files.js","bundle:clean":"rimraf dist node_modules/.cache","bundle":"rollup -c rollup.config.js","bs:watch":"bsb -make-world -w","docs:dev":"gatsby develop","build":"run-s bs:build bundle flowgen","bs:clean":"bsb -clean-world","clean":"run-s bs:clean bundle:clean"}},"1.4.0":{"version":"1.4.0","dist":{"tarball":"https://registry.npmjs.org/wonka/-/wonka-1.4.0.tgz","shasum":"e085d2751c5532605e449186525c1bd4a52c4cbc","integrity":"sha512-m/wGinkE68T8jytnns5Ma2XkyFCjRMzMiuUOhy6YMbFDuuEnKQarvupAf/mcQudKBmjmf2rKFIbB7svRJUO6GQ=="},"bin":null,"dependencies":{"bs-rebel":"^0.2.3"},"optionalDependencies":{},"peerDependencies":{},"peerDependenciesMeta":{},"os":[],"cpu":[],"scripts":{"test":"jest","test:watch":"jest --watch","prebundlesize":"run-s bundle","terser":"run-p terser:es terser:cjs","coverage":"jest -c ./.jest.coverage.json --coverage","build":"bsb -make-world","prettier":"prettier --write ./dist/*.js","terser:es":"terser --config-file .terser.config.json --module -o ./dist/wonka.es.js ./dist/wonka.es.js","prepublishOnly":"run-s clean build bundle test","bundle":"microbundle --external none --no-compress --no-sourcemap --format es,cjs","watch":"bsb -make-world -w","terser:cjs":"terser --config-file .terser.config.json -o ./dist/wonka.js ./dist/wonka.js","postbundle":"run-s terser prettier","bundlesize":"bundlesize","clean":"bsb -clean-world","prebundle":"rimraf ./dist"}},"4.0.6":{"version":"4.0.6","dist":{"tarball":"https://registry.npmjs.org/wonka/-/wonka-4.0.6.tgz","shasum":"810e080f14f1ada7e5561b5504292de7fd5fdb1a","integrity":"sha512-TYvOaAEyw50aracY97gXTcP5eifVNp+djbXbsBmR32luS4OTdIOBLasKH7SIlYVCATS5O5Fk0bP1gocg20AbIg=="},"bin":null,"dependencies":{},"optionalDependencies":{},"peerDependencies":{},"peerDependenciesMeta":{},"os":[],"cpu":[],"scripts":{"bundle:clean":"rimraf dist node_modules/.cache","bs:build":"bsb -make-world","bs:watch":"bsb -make-world -w","docs:dev":"gatsby develop","check":"run-s check:ts check:flow","check:ts":"tsc --noEmit","prepublishOnly":"run-s clean build check test","check:flow":"flow focus-check ./src/helpers/Wonka_flow_test.js","clean":"run-s bs:clean bundle:clean","build":"run-s bs:build bundle flowgen","test":"jest","docs:build":"gatsby build","bundle":"rollup -c rollup.config.js","bs:clean":"bsb -clean-world","refmt":"bsrefmt --in-place **/**/*.{re,rei}","flowgen":"./scripts/generate-flow-files.js"}},"4.0.7":{"version":"4.0.7","dist":{"tarball":"https://registry.npmjs.org/wonka/-/wonka-4.0.7.tgz","shasum":"b4934685bd2449367bd72ce7770bfe3e6cc8a68b","integrity":"sha512-Uhyl2cgWCUksYtU0Jt8MSzKUqK4BVUrewWxnn1YlKL3Zco4sDcCUDkbgH0i762HJs1rtsq03cfzsCWxJKaDgVg=="},"bin":null,"dependencies":{},"optionalDependencies":{},"peerDependencies":{},"peerDependenciesMeta":{},"os":[],"cpu":[],"scripts":{"docs:dev":"gatsby develop","bundle":"rollup -c rollup.config.js","check":"run-s check:ts check:flow","prepublishOnly":"run-s clean build check test","bs:build":"bsb -make-world","bs:clean":"bsb -clean-world","build":"run-s bs:build bundle flowgen","bs:watch":"bsb -make-world -w","test":"jest","check:flow":"flow focus-check ./src/helpers/Wonka_flow_test.js","docs:build":"gatsby build","refmt":"bsrefmt --in-place **/**/*.{re,rei}","bundle:clean":"rimraf dist node_modules/.cache","clean":"run-s bs:clean bundle:clean","flowgen":"./scripts/generate-flow-files.js","check:ts":"tsc --noEmit"}},"4.0.14":{"version":"4.0.14","dist":{"tarball":"https://registry.npmjs.org/wonka/-/wonka-4.0.14.tgz","shasum":"77d680a84e575ed15a9f975eb87d6c530488f3a4","integrity":"sha512-v9vmsTxpZjrA8CYfztbuoTQSHEsG3ZH+NCYfasHm0V3GqBupXrjuuz0RJyUaw2cRO7ouW2js0P6i853/qxlDcA=="},"bin":null,"dependencies":{},"optionalDependencies":{},"peerDependencies":{},"peerDependenciesMeta":{},"os":[],"cpu":[],"scripts":{"docs:build":"gatsby build","bundle":"rollup -c rollup.config.js","docs:dev":"gatsby develop","check:flow":"flow focus-check ./src/helpers/Wonka_flow_test.js","bs:clean":"bsb -clean-world","prepublishOnly":"run-s clean build check test","build":"run-s bs:build bundle flowgen","clean":"run-s bs:clean bundle:clean","check":"run-s check:ts check:flow","bundle:clean":"rimraf dist node_modules/.cache","bs:build":"bsb -make-world","check:ts":"tsc --noEmit","test":"jest","refmt":"bsrefmt --in-place **/**/*.{re,rei}","flowgen":"./scripts/generate-flow-files.js","bs:watch":"bsb -make-world -w"}},"1.1.6":{"version":"1.1.6","dist":{"tarball":"https://registry.npmjs.org/wonka/-/wonka-1.1.6.tgz","shasum":"8013305a62104af64350beeeffefe4e39d25c13f","integrity":"sha512-12qc1nx+3IgL7eJmupOhvFumtSHD6vbd3bA6OaCrVKJbuOKRvXsMBjuiaaIhblOdoFDrPD/RT9gLebtAIZcHcA=="},"bin":null,"dependencies":{"bs-rebel":"^0.2.3"},"optionalDependencies":{},"peerDependencies":{},"peerDependenciesMeta":{},"os":[],"cpu":[],"scripts":{"bundle":"microbundle --external none --no-compress --no-sourcemap --format es,cjs","test":"jest","terser":"run-p terser:es terser:cjs","prepublishOnly":"run-s clean build bundle test","test:watch":"jest --watch","build":"bsb -make-world","postbundle":"run-s terser prettier","watch":"bsb -make-world -w","coverage":"jest -c ./.jest.coverage.json --coverage","clean":"bsb -clean-world","prebundle":"rimraf ./dist","terser:cjs":"terser --config-file .terser.config.json -o ./dist/wonka.js ./dist/wonka.js","terser:es":"terser --config-file .terser.config.json --module -o ./dist/wonka.es.js ./dist/wonka.es.js","prebundlesize":"run-s bundle","prettier":"prettier --write ./dist/*.js","bundlesize":"bundlesize"}},"6.2.6":{"version":"6.2.6","dist":{"tarball":"https://registry.npmjs.org/wonka/-/wonka-6.2.6.tgz","shasum":"8194cf9fbc69de1bf25e9df69af84f08747843be","integrity":"sha512-ExUBenRwEyf8YswAVOFZDmAdiUMgpnuyDV28G9bF+73o2hnhAG9tLqnn7LmtWgB2KCFQdWywbUfvUW3UgxARew=="},"bin":null,"dependencies":{},"optionalDependencies":{},"peerDependencies":{},"peerDependenciesMeta":{},"os":[],"cpu":[],"scripts":{"test":"vitest run","changeset:version":"changeset version && pnpm install --lockfile-only","changeset:publish":"changeset publish","lint":"eslint --ext=js,ts .","clean":"rimraf dist node_modules/.cache","build":"rollup -c scripts/rollup.config.mjs","check":"tsc"}},"6.3.1":{"version":"6.3.1","dist":{"tarball":"https://registry.npmjs.org/wonka/-/wonka-6.3.1.tgz","shasum":"315b2a91e134c4032980836e6d97e13d0927634d","integrity":"sha512-nJyGPcjuBiaLFn8QAlrHd+QjV9AlPO7snOWAhgx6aX0nQLMV6Wi0nqfrkmsXIH0efngbDOroOz2QyLnZMF16Hw=="},"bin":null,"dependencies":{},"optionalDependencies":{},"peerDependencies":{},"peerDependenciesMeta":{},"os":[],"cpu":[],"scripts":{"test":"vitest run","changeset:version":"changeset version && pnpm install --lockfile-only","lint":"eslint --ext=js,ts .","build":"rollup -c scripts/rollup.config.mjs","check":"tsc","changeset:publish":"changeset publish","clean":"rimraf dist node_modules/.cache"}},"3.0.0-2.beta":{"version":"3.0.0-2.beta","dist":{"tarball":"https://registry.npmjs.org/wonka/-/wonka-3.0.0-2.beta.tgz","shasum":"aa952bc91e9e5977cb49bd729297d885c5e68ba2","integrity":"sha512-EXtmHv3O6V0NELa41FW5KQN5X8htUl3a9SsneMVGMYXIbHaqgrpQPvMTnks4tM6p5tsvRTgACXBzUGieP/4H5A=="},"bin":null,"dependencies":{},"optionalDependencies":{},"peerDependencies":{},"peerDependenciesMeta":{},"os":[],"cpu":[],"scripts":{"watch":"bsb -make-world -w","coverage":"jest -c ./.jest.coverage.json --coverage","refmt":"bsrefmt --in-place **/**/*.{re,rei}","flowgen":"./scripts/generate-flow-files.js","build":"bsb -make-world","prepublishOnly":"run-s clean build bundle flowgen test","clean":"bsb -clean-world","test:watch":"jest --watch","test":"jest","bundle":"rollup -c rollup.config.js"}},"3.2.1":{"version":"3.2.1","dist":{"tarball":"https://registry.npmjs.org/wonka/-/wonka-3.2.1.tgz","shasum":"f66123fabbb260f23a4e89f1526317169203e258","integrity":"sha512-LpquZ9PJtYJ31AlMPp5tEba1y+S+wUmY7OyFLGZCmGSNO1ZOTTZGp/HbieFzP5fVJ9fWXCus3ecgDjwAssHSGg=="},"bin":null,"dependencies":{},"optionalDependencies":{},"peerDependencies":{},"peerDependenciesMeta":{},"os":[],"cpu":[],"scripts":{"prepublishOnly":"run-s clean build bundle flowgen check test","build":"bsb -make-world","codecov":"codecov","flowgen":"./scripts/generate-flow-files.js","coverage":"jest -c ./.jest.coverage.json --coverage","docs:dev":"gatsby develop","docs:build":"gatsby build","check":"tsc --noEmit","clean":"bsb -clean-world","test":"jest","test:watch":"jest --watch","refmt":"bsrefmt --in-place **/**/*.{re,rei}","bundle":"rollup -c rollup.config.js","watch":"bsb -make-world -w"}},"4.0.0-rc.0":{"version":"4.0.0-rc.0","dist":{"tarball":"https://registry.npmjs.org/wonka/-/wonka-4.0.0-rc.0.tgz","shasum":"f97942b142071836eed2b6bea39952da304bc38b","integrity":"sha512-q4bbHGO2Uw/ymQVa+hgRn8X2gJioSG7fcgNBuGKf+hBB2D/Uk3X9tgUYrBlW9XjzMwhjQdhPGAV7hZO6K0h89g=="},"bin":null,"dependencies":{},"optionalDependencies":{},"peerDependencies":{},"peerDependenciesMeta":{},"os":[],"cpu":[],"scripts":{"bundle:clean":"rimraf dist node_modules/.cache","prepublishOnly":"run-s clean build bundle flowgen check test","docs:build":"gatsby build","bs:clean":"bsb -clean-world","flowgen":"./scripts/generate-flow-files.js","docs:dev":"gatsby develop","check":"tsc --noEmit","bs:watch":"bsb -make-world -w","refmt":"bsrefmt --in-place **/**/*.{re,rei}","clean":"run-s bs:clean bundle:clean","build":"run-s bs:build bundle flowgen","test":"jest","bs:build":"bsb -make-world","bundle":"rollup -c rollup.config.js"}},"4.0.0-rc.3":{"version":"4.0.0-rc.3","dist":{"tarball":"https://registry.npmjs.org/wonka/-/wonka-4.0.0-rc.3.tgz","shasum":"a7711f74b767aba210bc87de9b683d4fa707c050","integrity":"sha512-xgM97k4bfmi0+Lgn8oMY5VUmKLRVzCPPyMtvDSP2i/DKXd7jnTrrkcE5l3A4tEff7d/uP3fVzicWrK/OxeXP8A=="},"bin":null,"dependencies":{},"optionalDependencies":{},"peerDependencies":{},"peerDependenciesMeta":{},"os":[],"cpu":[],"scripts":{"bundle":"rollup -c rollup.config.js","clean":"run-s bs:clean bundle:clean","prepublishOnly":"run-s clean build bundle flowgen check test","build":"run-s bs:build bundle flowgen","bs:clean":"bsb -clean-world","bs:watch":"bsb -make-world -w","test":"jest","flowgen":"./scripts/generate-flow-files.js","bs:build":"bsb -make-world","refmt":"bsrefmt --in-place **/**/*.{re,rei}","docs:dev":"gatsby develop","bundle:clean":"rimraf dist node_modules/.cache","docs:build":"gatsby build","check":"tsc --noEmit"}},"6.2.4":{"version":"6.2.4","dist":{"tarball":"https://registry.npmjs.org/wonka/-/wonka-6.2.4.tgz","shasum":"e37c601a84efffe97a36b34455c8383b82c5e9f1","integrity":"sha512-+q0VMDFqLzu+NAOdhmebQb46Fprip1zV1I/AhKYG4MAtru03R5L6MU89XQK59YDiPL7ELDZEEgZTGtCJ0BWL6g=="},"bin":null,"dependencies":{},"optionalDependencies":{},"peerDependencies":{},"peerDependenciesMeta":{},"os":[],"cpu":[],"scripts":{"check":"tsc","build":"rollup -c scripts/rollup.config.mjs","lint":"eslint --ext=js,ts .","clean":"rimraf dist node_modules/.cache","changeset:version":"changeset version && pnpm install --lockfile-only","changeset:publish":"changeset publish","test":"vitest run"}},"0.1.0-0":{"version":"0.1.0-0","dist":{"tarball":"https://registry.npmjs.org/wonka/-/wonka-0.1.0-0.tgz","shasum":"80bf413d006c17ddbca9f7fc23f7c37905d27065","integrity":"sha512-RdMVVZEUc6czPd0kd/+3vyu9gCcDR719wCg+oxD9fiam1Vyhu/meDShuEvLlihWL9GyAdajjMYzjhHDnN5T1/Q=="},"bin":null,"dependencies":{},"optionalDependencies":{},"peerDependencies":{"bs-platform":">=2.2.0"},"peerDependenciesMeta":{},"os":[],"cpu":[],"scripts":{"coverage":"jest -c ./.jest.coverage.json --coverage","bundlesize":"bundlesize","watch":"bsb -make-world -w","clean":"bsb -clean-world","test":"jest","prebundlesize":"run-s bundle","build":"bsb -make-world","prepublishOnly":"run-s clean build test bundle","prebundle":"run-s build","test:watch":"jest --watch","bundle":"microbundle -i ./.index.js"}},"4.0.0-rc.1":{"version":"4.0.0-rc.1","dist":{"tarball":"https://registry.npmjs.org/wonka/-/wonka-4.0.0-rc.1.tgz","shasum":"bc4bf4a9f876cb729bada9abf1eebfca91fa9032","integrity":"sha512-ew6uhzJF62P3dfQI+yUA75OSeyGWhBN9YLXqUiJPnO+QsqwZlu8mIJbrXs+MXPgkIC6pDerF6hxP/iPmOdWhmw=="},"bin":null,"dependencies":{},"optionalDependencies":{},"peerDependencies":{},"peerDependenciesMeta":{},"os":[],"cpu":[],"scripts":{"docs:build":"gatsby build","flowgen":"./scripts/generate-flow-files.js","clean":"run-s bs:clean bundle:clean","bs:watch":"bsb -make-world -w","test":"jest","refmt":"bsrefmt --in-place **/**/*.{re,rei}","build":"run-s bs:build bundle flowgen","check":"tsc --noEmit","bundle":"rollup -c rollup.config.js","prepublishOnly":"run-s clean build bundle flowgen check test","bs:clean":"bsb -clean-world","docs:dev":"gatsby develop","bundle:clean":"rimraf dist node_modules/.cache","bs:build":"bsb -make-world"}},"3.1.1":{"version":"3.1.1","dist":{"tarball":"https://registry.npmjs.org/wonka/-/wonka-3.1.1.tgz","shasum":"c948e8299468dd87eb0d6fc9b5647f7848a85af2","integrity":"sha512-UT65glpq1Bl9DaLwMJp6/EvsL+juqdkvJpAb2xsmUqmWLPkwIGB0/kIh8DHr3dem0UXHcgIDBizmH3xnnScguA=="},"bin":null,"dependencies":{},"optionalDependencies":{},"peerDependencies":{},"peerDependenciesMeta":{},"os":[],"cpu":[],"scripts":{"prepublishOnly":"run-s clean build bundle flowgen check test","docs:dev":"gatsby develop","build":"bsb -make-world","watch":"bsb -make-world -w","test":"jest","docs:build":"gatsby build","coverage":"jest -c ./.jest.coverage.json --coverage","check":"tsc --noEmit","refmt":"bsrefmt --in-place **/**/*.{re,rei}","bundle":"rollup -c rollup.config.js","codecov":"codecov","test:watch":"jest --watch","clean":"bsb -clean-world","flowgen":"./scripts/generate-flow-files.js"}},"0.0.0-canary-20230318003145":{"version":"0.0.0-canary-20230318003145","dist":{"tarball":"https://registry.npmjs.org/wonka/-/wonka-0.0.0-canary-20230318003145.tgz","shasum":"33eddfaee8944949feda8b28989850fae9f5c872","integrity":"sha512-H6pWKmPSjoK4+XztzM/pMwStncVX93GDoGsO8nbWDZXVkbarDlMwSi4HcY9EGh/YwXPtFmhHWr138Uk/+0ZHug=="},"bin":null,"dependencies":{},"optionalDependencies":{},"peerDependencies":{},"peerDependenciesMeta":{},"os":[],"cpu":[],"scripts":{"check":"tsc","test":"vitest run","changeset:publish":"changeset publish","build":"rollup -c scripts/rollup.config.mjs","clean":"rimraf dist node_modules/.cache","changeset:version":"changeset version && pnpm install --lockfile-only","lint":"eslint --ext=js,ts ."}},"0.0.0-canary-20230328165206":{"version":"0.0.0-canary-20230328165206","dist":{"tarball":"https://registry.npmjs.org/wonka/-/wonka-0.0.0-canary-20230328165206.tgz","shasum":"2d325094ae4d4caed1c4a31ca7c1330ff74af9dd","integrity":"sha512-9a/Vh+41TQbK1Cebg3gfencT9q8acxzahf+SyczKR+WVFgXPeVgEkJ8kf8idLe5wkscwMFk7ur7IX9tl4rvzEQ=="},"bin":null,"dependencies":{},"optionalDependencies":{},"peerDependencies":{},"peerDependenciesMeta":{},"os":[],"cpu":[],"scripts":{"build":"rollup -c scripts/rollup.config.mjs","clean":"rimraf dist node_modules/.cache","changeset:publish":"changeset publish","test":"vitest run","check":"tsc","changeset:version":"changeset version && pnpm install --lockfile-only","lint":"eslint --ext=js,ts ."}},"6.3.4-canary-f028aa3":{"version":"6.3.4-canary-f028aa3","dist":{"tarball":"https://registry.npmjs.org/wonka/-/wonka-6.3.4-canary-f028aa3.tgz","shasum":"54cdb6f574436bdbb99556d6df893fb49f6dc9a9","integrity":"sha512-ZiPpvf5GpSJmS0cmthWPOTcn28WoygGtMK5orwKWycGwkfPVMIgdK8LPQ4W2knwsr3TxFNEqDqBurcG5jVLxkA=="},"bin":null,"dependencies":{},"optionalDependencies":{},"peerDependencies":{},"peerDependenciesMeta":{},"os":[],"cpu":[],"scripts":{"test":"vitest run","lint":"eslint --ext=js,ts .","check":"tsc","build":"rollup -c scripts/rollup.config.mjs","clean":"rimraf dist node_modules/.cache","changeset:version":"changeset version && pnpm install --lockfile-only","changeset:publish":"changeset publish"}},"1.1.3":{"version":"1.1.3","dist":{"tarball":"https://registry.npmjs.org/wonka/-/wonka-1.1.3.tgz","shasum":"062ad09746aa377f0f3b9ddb69ccb6e7ab438250","integrity":"sha512-yhM18dXs0zI4ubme6HpvpmTlPXnZP1EjsVZcOhL4m2mUwIsjES6kDaHzK8IhCeGsJZAqam4LeeWAVOcF48EwFg=="},"bin":null,"dependencies":{"bs-rebel":"^0.2.3"},"optionalDependencies":{},"peerDependencies":{},"peerDependenciesMeta":{},"os":[],"cpu":[],"scripts":{"bundlesize":"bundlesize","clean:dist":"rimraf dist","watch":"bsb -make-world -w","clean:bs":"bsb -clean-world","test":"jest","coverage":"jest -c ./.jest.coverage.json --coverage","test:watch":"jest --watch","prebundlesize":"run-s bundle","prepublishOnly":"run-s clean build bundle test","bundle":"microbundle --external none --no-compress --format es,cjs","clean":"run-p clean:bs clean:dist","build":"bsb -make-world"}},"2.0.1":{"version":"2.0.1","dist":{"tarball":"https://registry.npmjs.org/wonka/-/wonka-2.0.1.tgz","shasum":"3769f9b050683edf2280e04d2b01afbdfe5fd9d4","integrity":"sha512-s0nGPVbbA9a0FhUarNJino4i1J1UyQ5rGA1MmA65U/+xUXmBQEw4cCKceRXkDhgL8ZJ2HVhvxthHFZZTf02gBA=="},"bin":null,"dependencies":{"bs-rebel":"^0.2.3"},"optionalDependencies":{},"peerDependencies":{},"peerDependenciesMeta":{},"os":[],"cpu":[],"scripts":{"test":"jest","watch":"bsb -make-world -w","prebundle":"rimraf ./dist","coverage":"jest -c ./.jest.coverage.json --coverage","bundle":"microbundle --external none --no-compress --no-sourcemap --format es,cjs","clean":"bsb -clean-world","postbundle":"run-s terser prettier","prebundlesize":"run-s bundle","test:watch":"jest --watch","build":"bsb -make-world","prepublishOnly":"run-s clean build bundle test","bundlesize":"bundlesize","terser":"run-p terser:es terser:cjs","terser:cjs":"terser --config-file .terser.config.json -o ./dist/wonka.js ./dist/wonka.js","prettier":"prettier --write ./dist/*.js","terser:es":"terser --config-file .terser.config.json --module -o ./dist/wonka.es.js ./dist/wonka.es.js"}},"0.1.0-4":{"version":"0.1.0-4","dist":{"tarball":"https://registry.npmjs.org/wonka/-/wonka-0.1.0-4.tgz","shasum":"b922ad9e79a0d01bd0945af63376fd9dd1b74eac","integrity":"sha512-hhI8gUc96Qnc9OY4X45HK/qDxlp54N/yrnLtV4/S+URSApMpcDxMZsFczEehzGF/c9H8vWgXPJjNFuXsfqpoaA=="},"bin":null,"dependencies":{},"optionalDependencies":{},"peerDependencies":{"bs-platform":">=2.2.0"},"peerDependenciesMeta":{},"os":[],"cpu":[],"scripts":{"prebundle":"run-s build","prebundlesize":"run-s bundle","test":"jest","bundlesize":"bundlesize","watch":"bsb -make-world -w","coverage":"jest -c ./.jest.coverage.json --coverage","prepublishOnly":"run-s clean build test bundle","bundle":"microbundle -i ./.index.js","build":"bsb -make-world","test:watch":"jest --watch","clean":"bsb -clean-world"}},"0.0.0-canary-20230425125537":{"version":"0.0.0-canary-20230425125537","dist":{"tarball":"https://registry.npmjs.org/wonka/-/wonka-0.0.0-canary-20230425125537.tgz","shasum":"bb4133b19904121c80e3c1709c9eab7bb400d386","integrity":"sha512-D/nqGLen+maJKsmySXurL2A86lMWDVn78q4NRpETPqaezdTtW5y8bp30LjO2SfkeBG60tWLd7uVQcTMprwN4NQ=="},"bin":null,"dependencies":{},"optionalDependencies":{},"peerDependencies":{},"peerDependenciesMeta":{},"os":[],"cpu":[],"scripts":{"check":"tsc","clean":"rimraf dist node_modules/.cache","changeset:version":"changeset version && pnpm install --lockfile-only","changeset:publish":"changeset publish","lint":"eslint --ext=js,ts .","test":"vitest run","build":"rollup -c scripts/rollup.config.mjs"}},"6.0.0":{"version":"6.0.0","dist":{"tarball":"https://registry.npmjs.org/wonka/-/wonka-6.0.0.tgz","shasum":"38cd39a517fc3ff721ea3bf353642b353bf48860","integrity":"sha512-TEiIOqkhQXbcmL1RrjxPCzTX15V5FSyJvZRSiTxvgTgrJMaOVKmzGTdRVh349CfaNo9dsIhWDyg1/GNq4NWrEg=="},"bin":null,"dependencies":{},"optionalDependencies":{},"peerDependencies":{},"peerDependenciesMeta":{},"os":[],"cpu":[],"scripts":{"check":"tsc","test":"jest","build":"rollup -c rollup.config.js","lint":"eslint --ext=js,ts .","clean":"rimraf dist node_modules/.cache","prepublishOnly":"run-s clean build check test"}},"1.2.0":{"version":"1.2.0","dist":{"tarball":"https://registry.npmjs.org/wonka/-/wonka-1.2.0.tgz","shasum":"9a34d728c1c19d149f06ee039def1f7c5bab4b21","integrity":"sha512-pntf3ITidkXvnfShbpXDkJ6pAAmoQlYg/3D0YL0bOvMcH8wSl+ATY9T/79xqOQu6kWqFBhj756b1jzFeHbQWHg=="},"bin":null,"dependencies":{"bs-rebel":"^0.2.3"},"optionalDependencies":{},"peerDependencies":{},"peerDependenciesMeta":{},"os":[],"cpu":[],"scripts":{"terser:cjs":"terser --config-file .terser.config.json -o ./dist/wonka.js ./dist/wonka.js","terser:es":"terser --config-file .terser.config.json --module -o ./dist/wonka.es.js ./dist/wonka.es.js","build":"bsb -make-world","terser":"run-p terser:es terser:cjs","prettier":"prettier --write ./dist/*.js","prebundle":"rimraf ./dist","test:watch":"jest --watch","prepublishOnly":"run-s clean build bundle test","bundlesize":"bundlesize","watch":"bsb -make-world -w","bundle":"microbundle --external none --no-compress --no-sourcemap --format es,cjs","postbundle":"run-s terser prettier","clean":"bsb -clean-world","coverage":"jest -c ./.jest.coverage.json --coverage","prebundlesize":"run-s bundle","test":"jest"}},"1.0.1":{"version":"1.0.1","dist":{"tarball":"https://registry.npmjs.org/wonka/-/wonka-1.0.1.tgz","shasum":"4076a7f3408388dc2988cff8fd19eff954c3d9bb","integrity":"sha512-erzwgjLeDTd3+pAZoJ99jJrnlc+MRD2KCfez8Wp4+UeeVwp91ieDuJehpCUUMJBlq5wPuj9hdDUBgA7cmTs5rA=="},"bin":null,"dependencies":{"bs-rebel":"^0.2.2"},"optionalDependencies":{},"peerDependencies":{"bs-platform":">=2.2.0"},"peerDependenciesMeta":{},"os":[],"cpu":[],"scripts":{"test:watch":"jest --watch","prepublishOnly":"run-s clean build test","build":"bsb -make-world","clean":"bsb -clean-world","test":"jest","coverage":"jest -c ./.jest.coverage.json --coverage","watch":"bsb -make-world -w"}},"1.1.4":{"version":"1.1.4","dist":{"tarball":"https://registry.npmjs.org/wonka/-/wonka-1.1.4.tgz","shasum":"dbbf0c4596f833c03d094e3d5d1f405cfe4e8560","integrity":"sha512-pnWcRZ9ODdY4Za+ipyvT39FxyQb3XwddZIN4DPb02i4+D4WZP9p51XkyiavvSvzmyPLD7Mg6esI3dA/ZHh+RiA=="},"bin":null,"dependencies":{"bs-rebel":"^0.2.3"},"optionalDependencies":{},"peerDependencies":{},"peerDependenciesMeta":{},"os":[],"cpu":[],"scripts":{"build":"bsb -make-world","clean":"run-p clean:bs clean:dist","bundle":"microbundle --external none --no-compress --format es,cjs","test":"jest","coverage":"jest -c ./.jest.coverage.json --coverage","clean:bs":"bsb -clean-world","clean:dist":"rimraf dist","test:watch":"jest --watch","prebundlesize":"run-s bundle","bundlesize":"bundlesize","prepublishOnly":"run-s clean build bundle test","watch":"bsb -make-world -w"}},"6.2.1":{"version":"6.2.1","dist":{"tarball":"https://registry.npmjs.org/wonka/-/wonka-6.2.1.tgz","shasum":"b09ccdceb7053c1753f6c1bb52d338ae21599059","integrity":"sha512-6et7xfxG/HtMwenqNsphz59PbYT1joKL11q9sY2en3JvzJZtR1alOROIl/1ibgBFdHJqKarF82Uqo1tr1ijzfQ=="},"bin":null,"dependencies":{},"optionalDependencies":{},"peerDependencies":{},"peerDependenciesMeta":{},"os":[],"cpu":[],"scripts":{"test":"vitest run","lint":"eslint --ext=js,ts .","check":"tsc","build":"rollup -c scripts/rollup.config.mjs","clean":"rimraf dist node_modules/.cache"}},"4.0.0":{"version":"4.0.0","dist":{"tarball":"https://registry.npmjs.org/wonka/-/wonka-4.0.0.tgz","shasum":"722930f8cdddb60b43706eb9de9ecdfe9c520a17","integrity":"sha512-5PG8O71yQp22eqrfqktthdzZcNvFKo8Z8eaLPyhpHR2W0J+BjF76qJUh3VjNtzGsyP5Bsp+csYvU5JvQ9li4kw=="},"bin":null,"dependencies":{},"optionalDependencies":{},"peerDependencies":{},"peerDependenciesMeta":{},"os":[],"cpu":[],"scripts":{"docs:dev":"gatsby develop","check":"tsc --noEmit","test":"jest","refmt":"bsrefmt --in-place **/**/*.{re,rei}","flowgen":"./scripts/generate-flow-files.js","clean":"run-s bs:clean bundle:clean","prepublishOnly":"run-s clean build check test","bs:watch":"bsb -make-world -w","docs:build":"gatsby build","bs:clean":"bsb -clean-world","bs:build":"bsb -make-world","bundle":"rollup -c rollup.config.js","build":"run-s bs:build bundle flowgen","bundle:clean":"rimraf dist node_modules/.cache"}},"1.3.2":{"version":"1.3.2","dist":{"tarball":"https://registry.npmjs.org/wonka/-/wonka-1.3.2.tgz","shasum":"8c3bd354e5b89bdf5b1f0b0d1cd9195b061eeb1a","integrity":"sha512-Yglan57EdaqiNlJ5GCvznn5uo9t3u+ox+TeYZIEgQCu9KEmaJwDE0VrCrlD1o7wS3Qh4qbW+7Em6/XWY1aNFTA=="},"bin":null,"dependencies":{"bs-rebel":"^0.2.3"},"optionalDependencies":{},"peerDependencies":{},"peerDependenciesMeta":{},"os":[],"cpu":[],"scripts":{"clean":"bsb -clean-world","test":"jest","build":"bsb -make-world","prepublishOnly":"run-s clean build bundle test","terser":"run-p terser:es terser:cjs","watch":"bsb -make-world -w","terser:es":"terser --config-file .terser.config.json --module -o ./dist/wonka.es.js ./dist/wonka.es.js","prettier":"prettier --write ./dist/*.js","prebundlesize":"run-s bundle","bundle":"microbundle --external none --no-compress --no-sourcemap --format es,cjs","test:watch":"jest --watch","bundlesize":"bundlesize","coverage":"jest -c ./.jest.coverage.json --coverage","postbundle":"run-s terser prettier","prebundle":"rimraf ./dist","terser:cjs":"terser --config-file .terser.config.json -o ./dist/wonka.js ./dist/wonka.js"}},"0.0.0-canary-20230327135055":{"version":"0.0.0-canary-20230327135055","dist":{"tarball":"https://registry.npmjs.org/wonka/-/wonka-0.0.0-canary-20230327135055.tgz","shasum":"b813d72cb7985f8c014649b9468c10993d1e5367","integrity":"sha512-s1KUIy6bXvKxgYM37XEn9nApoRWzvlM6EbbQLe+T8JkhfqoynqR1Q1IdNkC3UMN7BdBlDU/eo10WbimBuU8bEA=="},"bin":null,"dependencies":{},"optionalDependencies":{},"peerDependencies":{},"peerDependenciesMeta":{},"os":[],"cpu":[],"scripts":{"changeset:publish":"changeset publish","build":"rollup -c scripts/rollup.config.mjs","lint":"eslint --ext=js,ts .","clean":"rimraf dist node_modules/.cache","test":"vitest run","check":"tsc","changeset:version":"changeset version && pnpm install --lockfile-only"}},"4.0.13":{"version":"4.0.13","dist":{"tarball":"https://registry.npmjs.org/wonka/-/wonka-4.0.13.tgz","shasum":"8d188160bd5742870c78ede7a4eba686d089a33f","integrity":"sha512-aWg92IVvbP/kp+q9rw+k/Uw3C/S2J0dTDNhEhivGVH3GXJZgpFk2nuyVtiS7Y1d0UG3m4jvOrR7bPXim6D/TBg=="},"bin":null,"dependencies":{},"optionalDependencies":{},"peerDependencies":{},"peerDependenciesMeta":{},"os":[],"cpu":[],"scripts":{"test":"jest","bundle:clean":"rimraf dist node_modules/.cache","check:flow":"flow focus-check ./src/helpers/Wonka_flow_test.js","bundle":"rollup -c rollup.config.js","check":"run-s check:ts check:flow","bs:watch":"bsb -make-world -w","bs:clean":"bsb -clean-world","flowgen":"./scripts/generate-flow-files.js","bs:build":"bsb -make-world","docs:build":"gatsby build","build":"run-s bs:build bundle flowgen","docs:dev":"gatsby develop","prepublishOnly":"run-s clean build check test","check:ts":"tsc --noEmit","refmt":"bsrefmt --in-place **/**/*.{re,rei}","clean":"run-s bs:clean bundle:clean"}},"6.1.2":{"version":"6.1.2","dist":{"tarball":"https://registry.npmjs.org/wonka/-/wonka-6.1.2.tgz","shasum":"2c66fa5b26a12f002a03619b988258313d0b5352","integrity":"sha512-zNrXPMccg/7OEp9tSfFkMgTvhhowqasiSHdJ3eCZolXxVTV/aT6HUTofoZk9gwRbGoFey/Nss3JaZKUMKMbofg=="},"bin":null,"dependencies":{},"optionalDependencies":{},"peerDependencies":{},"peerDependenciesMeta":{},"os":[],"cpu":[],"scripts":{"build":"rollup -c rollup.config.js","prepublishOnly":"run-s clean build check test","check":"tsc","lint":"eslint --ext=js,ts .","clean":"rimraf dist node_modules/.cache","test":"vitest run"}},"6.1.1":{"version":"6.1.1","dist":{"tarball":"https://registry.npmjs.org/wonka/-/wonka-6.1.1.tgz","shasum":"134ece7d07848477e3a8b7d35f2333af2edde138","integrity":"sha512-shBtyZ0KFvUadtnDGlTRA4mF4pgcRoyZKikdputKhmShoXWcZDvlg6CUw6Jx9nTL7Ub8QUJoIarPpxdlosg9cw=="},"bin":null,"dependencies":{},"optionalDependencies":{},"peerDependencies":{},"peerDependenciesMeta":{},"os":[],"cpu":[],"scripts":{"build":"rollup -c rollup.config.js","check":"tsc","test":"vitest run","clean":"rimraf dist node_modules/.cache","lint":"eslint --ext=js,ts .","prepublishOnly":"run-s clean build check test"}}},"dist-tags":{"latest":"6.3.4","rc":"5.0.0-rc.1","canary":"6.3.4-canary-f028aa3"}}